box_manager/__init__.py
box_manager/cli.py
box_manager-0.1.1.dist-info/METADATA
box_manager-0.1.1.dist-info/WHEEL
box_manager-0.1.1.dist-info/entry_points.txt
box_manager-0.1.1.dist-info/top_level.txt
box_manager-0.1.1.dist-info/RECORD
