Metadata-Version: 2.4
Name: box-manager
Version: 0.1.1
Summary: Orchestration tool for managing systemd services and process priorities in Debian systems.
Author-email: rajatasusual <rajatasusual@github.com>
License-Expression: MIT
Project-URL: Homepage, https://github.com/rajatasusual/box-manager
Project-URL: Repository, https://github.com/rajatasusual/box-manager
Requires-Python: >=3.8
Requires-Dist: PyYAML>=6.0
Requires-Dist: click>=8.0
Provides-Extra: dev
Requires-Dist: pytest>=7.0; extra == "dev"
Requires-Dist: pytest-mock; extra == "dev"
